Metadata-Version: 2.4
Name: mcp-cldkctl
Version: 0.3.0
Summary: MCP server for Cloudeka cldkctl CLI integration with automatic environment fallback (Testing Version)
Project-URL: Homepage, https://github.com/cloudeka/mcp-cldkctl
Project-URL: Documentation, https://github.com/cloudeka/mcp-cldkctl#readme
Project-URL: Repository, https://github.com/cloudeka/mcp-cldkctl
Project-URL: Issues, https://github.com/cloudeka/mcp-cldkctl/issues
Author-email: Cloudeka MCP Team <support@cloudeka.id>
License: MIT
License-File: LICENSE
Keywords: cldkctl,cli,cloud,cloudeka,kubernetes,mcp,testing
Classifier: Development Status :: 4 - Beta
Classifier: Intended Audience :: Developers
Classifier: License :: OSI Approved :: MIT License
Classifier: Programming Language :: Python :: 3
Classifier: Programming Language :: Python :: 3.10
Classifier: Programming Language :: Python :: 3.11
Classifier: Programming Language :: Python :: 3.12
Classifier: Topic :: Software Development :: Libraries :: Python Modules
Classifier: Topic :: System :: Systems Administration
Classifier: Topic :: Utilities
Requires-Python: >=3.10
Requires-Dist: anyio>=3.0.0
Requires-Dist: mcp>=1.0.0
Requires-Dist: requests>=2.25.0
Provides-Extra: dev
Requires-Dist: black>=22.0.0; extra == 'dev'
Requires-Dist: flake8>=4.0.0; extra == 'dev'
Requires-Dist: isort>=5.0.0; extra == 'dev'
Requires-Dist: mypy>=0.991; extra == 'dev'
Requires-Dist: pytest-asyncio>=0.21.0; extra == 'dev'
Requires-Dist: pytest>=7.0.0; extra == 'dev'
